lapsepy/__init__.py
lapsepy/auth/__init__.py
lapsepy/auth/refresher.py
lapsepy/journal/__init__.py
lapsepy/journal/journal.py
lapsepy/journal/common/__init__.py
lapsepy/journal/common/exceptions.py
lapsepy/journal/common/utils.py
lapsepy/journal/factory/__init__.py
lapsepy/journal/factory/album_factory.py
lapsepy/journal/factory/factory.py
lapsepy/journal/factory/friends_factory.py
lapsepy/journal/factory/media_factory.py
lapsepy/journal/factory/profile_factory.py
lapsepy/journal/structures/__init__.py
lapsepy/journal/structures/album.py
lapsepy/journal/structures/comment.py
lapsepy/journal/structures/core.py
lapsepy/journal/structures/friendsfeed.py
lapsepy/journal/structures/options.py
lapsepy/journal/structures/profile.py
lapsepy/journal/structures/searches.py
lapsepy/journal/structures/snap.py
lapsepy/lapse/__init__.py
lapsepy/lapse/lapse.py
lapsepy-1.2.0.dist-info/LICENSE
lapsepy-1.2.0.dist-info/METADATA
lapsepy-1.2.0.dist-info/WHEEL
lapsepy-1.2.0.dist-info/top_level.txt
lapsepy-1.2.0.dist-info/RECORD
