Metadata-Version: 2.1
Name: lapsepy
Version: 1.2.0
Summary: A Python API wrapper for the social media app Lapse.
Home-page: https://github.com/quintindunn/lapsepy
Author: Quintin Dunn
Author-email: dunnquintin07@gmail.com
License: MIT
Keywords: social media,lapsepy,api,api wrapper
Classifier: Development Status :: 5 - Production/Stable
Classifier: Operating System :: Microsoft :: Windows :: Windows 10
Classifier: Programming Language :: Python :: 3
License-File: LICENSE
Requires-Dist: certifi ==2023.7.22
Requires-Dist: charset-normalizer ==3.3.0
Requires-Dist: idna ==3.4
Requires-Dist: Pillow ==10.1.0
Requires-Dist: requests ==2.31.0
Requires-Dist: urllib3 ==2.0.7
